pytwobit/__init__.py
pytwobit/data_view.py
pytwobit/remote_file.py
pytwobit/twobit.py
pytwobit-0.3.1.dist-info/LICENSE
pytwobit-0.3.1.dist-info/METADATA
pytwobit-0.3.1.dist-info/WHEEL
pytwobit-0.3.1.dist-info/top_level.txt
pytwobit-0.3.1.dist-info/RECORD
