Metadata-Version: 2.1
Name: pytwobit
Version: 0.3.1
Summary: A fast reader for local or remote UCSC twobit sequence files.
Home-page: https://github.com/jrobinso/pytwobit
Author: Jim Robinson
License: MIT
Classifier: Development Status :: 4 - Beta
Classifier: Intended Audience :: Developers
Classifier: License :: OSI Approved :: MIT License
Classifier: Programming Language :: Python :: 3.8
Classifier: Topic :: Scientific/Engineering :: Bio-Informatics
License-File: LICENSE
Requires-Dist: requests
